qolpy/__init__.py
qolpy/test.py
qolpy/colour/__init__.py
qolpy/colour/interface.py
qolpy/colour/main.py
qolpy/colour/switch.py
qolpy/date/__init__.py
qolpy/date/interface.py
qolpy/date/main.py
qolpy/date/switch.py
qolpy/logger/__init__.py
qolpy/logger/main.py
qolpy/number/__init__.py
qolpy/number/interface.py
qolpy/number/main.py
qolpy/string/__init__.py
qolpy/string/main.py
qolpy-0.2.0.dist-info/LICENSE
qolpy-0.2.0.dist-info/METADATA
qolpy-0.2.0.dist-info/WHEEL
qolpy-0.2.0.dist-info/top_level.txt
qolpy-0.2.0.dist-info/RECORD
