Metadata-Version: 2.1
Name: qolpy
Version: 0.2.0
Summary: A suite of random but useful functions that are aimed at giving you 'piece of cake' level comfortability
Home-page: https://github.com/cerebrusinc/qolpy.git
Author: Lewis Mosho Jr | Cerebrus Inc
Author-email: hello@cerebrus.dev
Project-URL: Bug Tracker, https://github.com/cerebrusinc/qolpy/issues
Classifier: License :: OSI Approved :: Apache Software License
Classifier: Programming Language :: Python :: 3
Classifier: Operating System :: OS Independent
Classifier: Topic :: Utilities
Classifier: Development Status :: 5 - Production/Stable
Classifier: Environment :: Plugins
Classifier: Intended Audience :: Developers
Classifier: Typing :: Typed
Requires-Python: >=3.0
License-File: LICENSE
